{
  "formatVersion": 1,
  "database": {
    "version": 1,
    "identityHash": "1b74de03abb4f9ee281b8e4da0b45ef3",
    "entities": [
      {
        "tableName": "SavedForm",
        "createSql": "CREATE TABLE IF NOT EXISTS `${TABLE_NAME}` (`id` INTEGER PRIMARY KEY AUTOINCREMENT NOT NULL, `form_id` TEXT, `form_name` TEXT, `is_synced` INTEGER, `form_category` TEXT, `request_object` TEXT, `createdDateTime` INTEGER)",
        "fields": [
          {
            "fieldPath": "id",
            "columnName": "id",
            "affinity": "INTEGER",
            "notNull": true
          },
          {
            "fieldPath": "formId",
            "columnName": "form_id",
            "affinity": "TEXT",
            "notNull": false
          },
          {
            "fieldPath": "formName",
            "columnName": "form_name",
            "affinity": "TEXT",
            "notNull": false
          },
          {
            "fieldPath": "isSynced",
            "columnName": "is_synced",
            "affinity": "INTEGER",
            "notNull": false
          },
          {
            "fieldPath": "formCategory",
            "columnName": "form_category",
            "affinity": "TEXT",
            "notNull": false
          },
          {
            "fieldPath": "requestObject",
            "columnName": "request_object",
            "affinity": "TEXT",
            "notNull": false
          },
          {
            "fieldPath": "createdAt",
            "columnName": "createdDateTime",
            "affinity": "INTEGER",
            "notNull": false
          }
        ],
        "primaryKey": {
          "columnNames": [
            "id"
          ],
          "autoGenerate": true
        },
        "indices": [],
        "foreignKeys": []
      },
      {
        "tableName": "FormData",
        "createSql": "CREATE TABLE IF NOT EXISTS `${TABLE_NAME}` (`id` TEXT NOT NULL, `name` TEXT, `components` TEXT, `is_active` TEXT, `is_editable` TEXT, `multiple_entry` TEXT, `category` TEXT, `microservice` TEXT, PRIMARY KEY(`id`))",
        "fields": [
          {
            "fieldPath": "id",
            "columnName": "id",
            "affinity": "TEXT",
            "notNull": true
          },
          {
            "fieldPath": "name",
            "columnName": "name",
            "affinity": "TEXT",
            "notNull": false
          },
          {
            "fieldPath": "components",
            "columnName": "components",
            "affinity": "TEXT",
            "notNull": false
          },
          {
            "fieldPath": "active",
            "columnName": "is_active",
            "affinity": "TEXT",
            "notNull": false
          },
          {
            "fieldPath": "editable",
            "columnName": "is_editable",
            "affinity": "TEXT",
            "notNull": false
          },
          {
            "fieldPath": "multipleEntry",
            "columnName": "multiple_entry",
            "affinity": "TEXT",
            "notNull": false
          },
          {
            "fieldPath": "category",
            "columnName": "category",
            "affinity": "TEXT",
            "notNull": false
          },
          {
            "fieldPath": "microService",
            "columnName": "microservice",
            "affinity": "TEXT",
            "notNull": false
          }
        ],
        "primaryKey": {
          "columnNames": [
            "id"
          ],
          "autoGenerate": false
        },
        "indices": [],
        "foreignKeys": []
      },
      {
        "tableName": "Modules",
        "createSql": "CREATE TABLE IF NOT EXISTS `${TABLE_NAME}` (`id` INTEGER PRIMARY KEY AUTOINCREMENT NOT NULL, `module_id` TEXT, `name` TEXT, `module` TEXT)",
        "fields": [
          {
            "fieldPath": "id",
            "columnName": "id",
            "affinity": "INTEGER",
            "notNull": true
          },
          {
            "fieldPath": "moduleId",
            "columnName": "module_id",
            "affinity": "TEXT",
            "notNull": false
          },
          {
            "fieldPath": "name",
            "columnName": "name",
            "affinity": "TEXT",
            "notNull": false
          },
          {
            "fieldPath": "module",
            "columnName": "module",
            "affinity": "TEXT",
            "notNull": false
          }
        ],
        "primaryKey": {
          "columnNames": [
            "id"
          ],
          "autoGenerate": true
        },
        "indices": [],
        "foreignKeys": []
      },
      {
        "tableName": "ReportData",
        "createSql": "CREATE TABLE IF NOT EXISTS `${TABLE_NAME}` (`id` TEXT NOT NULL, `name` TEXT, `description` TEXT, `url` TEXT, `categoryId` TEXT, `category` TEXT, `active` TEXT, `updatedAt` INTEGER, `createdAt` INTEGER, PRIMARY KEY(`id`))",
        "fields": [
          {
            "fieldPath": "id",
            "columnName": "id",
            "affinity": "TEXT",
            "notNull": true
          },
          {
            "fieldPath": "name",
            "columnName": "name",
            "affinity": "TEXT",
            "notNull": false
          },
          {
            "fieldPath": "description",
            "columnName": "description",
            "affinity": "TEXT",
            "notNull": false
          },
          {
            "fieldPath": "url",
            "columnName": "url",
            "affinity": "TEXT",
            "notNull": false
          },
          {
            "fieldPath": "categoryId",
            "columnName": "categoryId",
            "affinity": "TEXT",
            "notNull": false
          },
          {
            "fieldPath": "category",
            "columnName": "category",
            "affinity": "TEXT",
            "notNull": false
          },
          {
            "fieldPath": "active",
            "columnName": "active",
            "affinity": "TEXT",
            "notNull": false
          },
          {
            "fieldPath": "updatedAt",
            "columnName": "updatedAt",
            "affinity": "INTEGER",
            "notNull": false
          },
          {
            "fieldPath": "createdAt",
            "columnName": "createdAt",
            "affinity": "INTEGER",
            "notNull": false
          }
        ],
        "primaryKey": {
          "columnNames": [
            "id"
          ],
          "autoGenerate": false
        },
        "indices": [],
        "foreignKeys": []
      },
      {
        "tableName": "FormResult",
        "createSql": "CREATE TABLE IF NOT EXISTS `${TABLE_NAME}` (`result_id` TEXT NOT NULL, `form_id` TEXT, `form_title` TEXT, `result` TEXT, `form_name` TEXT, `form_status` INTEGER NOT NULL, `form_category` TEXT, `request_object` TEXT, `createdDateTime` INTEGER, `oid` TEXT, `formCategoryLocale` TEXT, `formNameLocale` TEXT, PRIMARY KEY(`result_id`))",
        "fields": [
          {
            "fieldPath": "_id",
            "columnName": "result_id",
            "affinity": "TEXT",
            "notNull": true
          },
          {
            "fieldPath": "formId",
            "columnName": "form_id",
            "affinity": "TEXT",
            "notNull": false
          },
          {
            "fieldPath": "formTitle",
            "columnName": "form_title",
            "affinity": "TEXT",
            "notNull": false
          },
          {
            "fieldPath": "result",
            "columnName": "result",
            "affinity": "TEXT",
            "notNull": false
          },
          {
            "fieldPath": "formName",
            "columnName": "form_name",
            "affinity": "TEXT",
            "notNull": false
          },
          {
            "fieldPath": "mFormStatus",
            "columnName": "form_status",
            "affinity": "INTEGER",
            "notNull": true
          },
          {
            "fieldPath": "formCategory",
            "columnName": "form_category",
            "affinity": "TEXT",
            "notNull": false
          },
          {
            "fieldPath": "requestObject",
            "columnName": "request_object",
            "affinity": "TEXT",
            "notNull": false
          },
          {
            "fieldPath": "createdAt",
            "columnName": "createdDateTime",
            "affinity": "INTEGER",
            "notNull": false
          },
          {
            "fieldPath": "oid",
            "columnName": "oid",
            "affinity": "TEXT",
            "notNull": false
          },
          {
            "fieldPath": "formCategoryLocale",
            "columnName": "formCategoryLocale",
            "affinity": "TEXT",
            "notNull": false
          },
          {
            "fieldPath": "formNameLocale",
            "columnName": "formNameLocale",
            "affinity": "TEXT",
            "notNull": false
          }
        ],
        "primaryKey": {
          "columnNames": [
            "result_id"
          ],
          "autoGenerate": false
        },
        "indices": [],
        "foreignKeys": []
      },
      {
        "tableName": "ProcessData",
        "createSql": "CREATE TABLE IF NOT EXISTS `${TABLE_NAME}` (`id` TEXT NOT NULL, `name` TEXT, `form_title` TEXT, `active` TEXT, `editable` TEXT, `multiple_entry` TEXT, `microservice` TEXT, `submit_count` TEXT, `category` TEXT, PRIMARY KEY(`id`))",
        "fields": [
          {
            "fieldPath": "id",
            "columnName": "id",
            "affinity": "TEXT",
            "notNull": true
          },
          {
            "fieldPath": "name",
            "columnName": "name",
            "affinity": "TEXT",
            "notNull": false
          },
          {
            "fieldPath": "formTitle",
            "columnName": "form_title",
            "affinity": "TEXT",
            "notNull": false
          },
          {
            "fieldPath": "active",
            "columnName": "active",
            "affinity": "TEXT",
            "notNull": false
          },
          {
            "fieldPath": "editable",
            "columnName": "editable",
            "affinity": "TEXT",
            "notNull": false
          },
          {
            "fieldPath": "multipleEntry",
            "columnName": "multiple_entry",
            "affinity": "TEXT",
            "notNull": false
          },
          {
            "fieldPath": "microservice",
            "columnName": "microservice",
            "affinity": "TEXT",
            "notNull": false
          },
          {
            "fieldPath": "submitCount",
            "columnName": "submit_count",
            "affinity": "TEXT",
            "notNull": false
          },
          {
            "fieldPath": "category",
            "columnName": "category",
            "affinity": "TEXT",
            "notNull": false
          }
        ],
        "primaryKey": {
          "columnNames": [
            "id"
          ],
          "autoGenerate": false
        },
        "indices": [],
        "foreignKeys": []
      },
      {
        "tableName": "UserAttendance",
        "createSql": "CREATE TABLE IF NOT EXISTS `${TABLE_NAME}` (`uid` TEXT NOT NULL, `latitude` REAL NOT NULL, `longitude` REAL NOT NULL, `Address` TEXT, `attendaceDate` INTEGER, `attendanceType` TEXT, `attendanceFormattedDate` TEXT, `time` TEXT, `isSync` INTEGER, PRIMARY KEY(`uid`))",
        "fields": [
          {
            "fieldPath": "uid",
            "columnName": "uid",
            "affinity": "TEXT",
            "notNull": true
          },
          {
            "fieldPath": "latitude",
            "columnName": "latitude",
            "affinity": "REAL",
            "notNull": true
          },
          {
            "fieldPath": "longitude",
            "columnName": "longitude",
            "affinity": "REAL",
            "notNull": true
          },
          {
            "fieldPath": "Address",
            "columnName": "Address",
            "affinity": "TEXT",
            "notNull": false
          },
          {
            "fieldPath": "attendaceDate",
            "columnName": "attendaceDate",
            "affinity": "INTEGER",
            "notNull": false
          },
          {
            "fieldPath": "attendanceType",
            "columnName": "attendanceType",
            "affinity": "TEXT",
            "notNull": false
          },
          {
            "fieldPath": "attendanceFormattedDate",
            "columnName": "attendanceFormattedDate",
            "affinity": "TEXT",
            "notNull": false
          },
          {
            "fieldPath": "time",
            "columnName": "time",
            "affinity": "TEXT",
            "notNull": false
          },
          {
            "fieldPath": "isSync",
            "columnName": "isSync",
            "affinity": "INTEGER",
            "notNull": false
          }
        ],
        "primaryKey": {
          "columnNames": [
            "uid"
          ],
          "autoGenerate": false
        },
        "indices": [],
        "foreignKeys": []
      }
    ],
    "views": [],
    "setupQueries": [
      "CREATE TABLE IF NOT EXISTS room_master_table (id INTEGER PRIMARY KEY,identity_hash TEXT)",
      "INSERT OR REPLACE INTO room_master_table (id,identity_hash) VALUES(42, \"1b74de03abb4f9ee281b8e4da0b45ef3\")"
    ]
  }
}